[
    {
        "Número Licitação": "000022023",
        "Código UG": "160086",
        "Nome UG": "GABINETE DO COMANDANTE DO EXERCITO",
        "Código Modalidade Compra": "-99",
        "Modalidade Compra": "Pregão - Registro de Preço",
        "Número Processo": "64536026417202331",
        "Objeto": "Objeto: Pregão Eletrônico - Aquisição de material permanente para o Gabinete do Comandante do Exército (Gab Cmt Ex).",
        "Situação Licitação": "Publicado",
        "Código Órgão Superior": "52000",
        "Nome Órgão Superior": "Ministério da Defesa",
        "Código Órgão": "52121",
        "Nome Órgão": "Comando do Exército",
        "UF": "DF",
        "Município": "BRASILIA",
        "Data Resultado Compra": "04/04/2024",
        "Data Abertura": "24/01/2024",
        "Valor Licitação": "0,00"
    },
    {
        "Número Licitação": "000062023",
        "Código UG": "200338",
        "Nome UG": "SUPERINTENDENCIA REGIONAL NO DISTRITO FEDERAL",
        "Código Modalidade Compra": "-99",
        "Modalidade Compra": "Pregão - Registro de Preço",
        "Número Processo": "08280.015486/2023",
        "Objeto": "Objeto: Pregão Eletrônico - Aquisição de materiais visando atender as atividades meio e fim da Superintendência da Polícia Federal no Distrito Federal, com materiais permanentes e de consumo. A aquisição está constante no Plano Anual de Contratação 2022/2023.",
        "Situação Licitação": "Publicado",
        "Código Órgão Superior": "30000",
        "Nome Órgão Superior": "Ministério da Justiça e Segurança Pública",
        "Código Órgão": "30108",
        "Nome Órgão": "Polícia Federal",
        "UF": "DF",
        "Município": "BRASILIA",
        "Data Resultado Compra": "05/04/2024",
        "Data Abertura": "08/12/2023",
        "Valor Licitação": "0,00"
    },
    {
        "Número Licitação": "000112023",
        "Código UG": "160062",
        "Nome UG": "CENTRO DE INTELIGENCIA DO EXERCITO",
        "Código Modalidade Compra": "-99",
        "Modalidade Compra": "Pregão - Registro de Preço",
        "Número Processo": "64503000684202366",
        "Objeto": "Objeto: Pregão Eletrônico - Aquisição de Painel Luminária de Embutir LED.",
        "Situação Licitação": "Publicado",
        "Código Órgão Superior": "52000",
        "Nome Órgão Superior": "Ministério da Defesa",
        "Código Órgão": "52121",
        "Nome Órgão": "Comando do Exército",
        "UF": "DF",
        "Município": "BRASILIA",
        "Data Resultado Compra": "04/04/2024",
        "Data Abertura": "21/03/2024",
        "Valor Licitação": "0,00"
    },
    {
        "Número Licitação": "000112023",
        "Código UG": "160186",
        "Nome UG": "BASE ADMINISTRATIVA DO QGEX",
        "Código Modalidade Compra": "-99",
        "Modalidade Compra": "Pregão - Registro de Preço",
        "Número Processo": "65304007248202327",
        "Objeto": "Objeto: Pregão Eletrônico - Contratação de serviços de buffet com arranjos florais e itens correlatos aos cerimoniais militares e eventos protocolares de caráter Institucional, conforme condições, quantidades e exigências estabelecidas neste Edital e no termo de referência.",
        "Situação Licitação": "Publicado",
        "Código Órgão Superior": "52000",
        "Nome Órgão Superior": "Ministério da Defesa",
        "Código Órgão": "52121",
        "Nome Órgão": "Comando do Exército",
        "UF": "DF",
        "Município": "BRASILIA",
        "Data Resultado Compra": "03/04/2024",
        "Data Abertura": "01/04/2024",
        "Valor Licitação": "0,00"
    },
    {
        "Número Licitação": "000122023",
        "Código UG": "160072",
        "Nome UG": "11. DEPOSITO DE SUPRIMENTO",
        "Código Modalidade Compra": "-99",
        "Modalidade Compra": "Pregão - Registro de Preço",
        "Número Processo": "64456004665202311",
        "Objeto": "Objeto: Pregão Eletrônico - Aquisição de gênero alimentícios (hortifrutigranjeiros). SERÃO ACEITAS APENAS OMS DO ARCCO.",
        "Situação Licitação": "Publicado",
        "Código Órgão Superior": "52000",
        "Nome Órgão Superior": "Ministério da Defesa",
        "Código Órgão": "52121",
        "Nome Órgão": "Comando do Exército",
        "UF": "DF",
        "Município": "BRASILIA",
        "Data Resultado Compra": "03/04/2024",
        "Data Abertura": "13/03/2024",
        "Valor Licitação": "0,00"
    },
    {
        "Número Licitação": "000122023",
        "Código UG": "160186",
        "Nome UG": "BASE ADMINISTRATIVA DO QGEX",
        "Código Modalidade Compra": "-99",
        "Modalidade Compra": "Pregão - Registro de Preço",
        "Número Processo": "65304007629202314",
        "Objeto": "Objeto: Pregão Eletrônico - Aquisição de gêneros alimentícios (hortifruti), em proveito dos militares do QGEx que compõem as diversas diretorias.",
        "Situação Licitação": "Publicado",
        "Código Órgão Superior": "52000",
        "Nome Órgão Superior": "Ministério da Defesa",
        "Código Órgão": "52121",
        "Nome Órgão": "Comando do Exército",
        "UF": "DF",
        "Município": "BRASILIA",
        "Data Resultado Compra": "03/04/2024",
        "Data Abertura": "28/02/2024",
        "Valor Licitação": "0,00"
    },
    {
        "Número Licitação": "000422023",
        "Código UG": "195006",
        "Nome UG": "CIA DE DES.DOS VALES DO S.FRANC.E DO PARNAIBA",
        "Código Modalidade Compra": "-99",
        "Modalidade Compra": "Pregão - Registro de Preço",
        "Número Processo": "59500002308202304",
        "Objeto": "Objeto: Pregão Eletrônico - Contratação de serviços de Execução de Capa Asfáltica com Concreto Betuminoso Usinado a Quente (CBUQ), de Pavimentação Asfáltica com CBUQ, de Pavimentação Asfáltica em Tratamento Superficial Duplo (TSD) e de Pavimentação em Bloco Intertravado de concreto (bloquete), na área de atuação da Codevasf, no Distrito Federal.",
        "Situação Licitação": "Evento de Resultado de Julgame",
        "Código Órgão Superior": "53000",
        "Nome Órgão Superior": "Ministério da Integração e do Desenvolvime",
        "Código Órgão": "22203",
        "Nome Órgão": "Companhia de Desenvolvimento dos Vales do Sã",
        "UF": "DF",
        "Município": "BRASILIA",
        "Data Resultado Compra": "04/04/2024",
        "Data Abertura": "16/11/2023",
        "Valor Licitação": "28978180,0000"
    },
    {
        "Número Licitação": "000902023",
        "Código UG": "155009",
        "Nome UG": "HOSPITAL UNIVERSITARIO DE BRASILIA",
        "Código Modalidade Compra": "-99",
        "Modalidade Compra": "Pregão - Registro de Preço",
        "Número Processo": "23522025132202355",
        "Objeto": "Objeto: Pregão Eletrônico - Aquisição de Insumos Gerais e EPIS para abastecer o Almoxarifado do Hospital Universitário de Brasília - HUB, referente ao Pregão 090/2023.",
        "Situação Licitação": "Publicado",
        "Código Órgão Superior": "26000",
        "Nome Órgão Superior": "Ministério da Educação",
        "Código Órgão": "26443",
        "Nome Órgão": "Empresa Brasileira de Serviços Hospitalares",
        "UF": "DF",
        "Município": "BRASILIA",
        "Data Resultado Compra": "04/04/2024",
        "Data Abertura": "29/11/2023",
        "Valor Licitação": "0,00"
    },
    {
        "Número Licitação": "001012023",
        "Código UG": "155009",
        "Nome UG": "HOSPITAL UNIVERSITARIO DE BRASILIA",
        "Código Modalidade Compra": "-99",
        "Modalidade Compra": "Pregão - Registro de Preço",
        "Número Processo": "23522011494202369",
        "Objeto": "Objeto: Pregão Eletrônico - Aquisição de Equipamentos Médicos Hospitalares para Unidade da Criança e Adolescente - UCA e demais setores do Hospital Universitário de Brasília - HUB, referente ao Pregão 101/2023.",
        "Situação Licitação": "Publicado",
        "Código Órgão Superior": "26000",
        "Nome Órgão Superior": "Ministério da Educação",
        "Código Órgão": "26443",
        "Nome Órgão": "Empresa Brasileira de Serviços Hospitalares",
        "UF": "DF",
        "Município": "BRASILIA",
        "Data Resultado Compra": "04/04/2024",
        "Data Abertura": "21/11/2023",
        "Valor Licitação": "0,00"
    },
    {
        "Número Licitação": "001082023",
        "Código UG": "155009",
        "Nome UG": "HOSPITAL UNIVERSITARIO DE BRASILIA",
        "Código Modalidade Compra": "-99",
        "Modalidade Compra": "Pregão - Registro de Preço",
        "Número Processo": "23522025568202344",
        "Objeto": "Objeto: Pregão Eletrônico - Aquisição de Insumos Gerais para a Unidade de Anatomia Patológica do Hospital Universitário de Brasília - HUB, Conforme Pregão 108/2023.",
        "Situação Licitação": "Publicado",
        "Código Órgão Superior": "26000",
        "Nome Órgão Superior": "Ministério da Educação",
        "Código Órgão": "26443",
        "Nome Órgão": "Empresa Brasileira de Serviços Hospitalares",
        "UF": "DF",
        "Município": "BRASILIA",
        "Data Resultado Compra": "05/04/2024",
        "Data Abertura": "02/02/2024",
        "Valor Licitação": "0,00"
    },
    {
        "Número Licitação": "001242023",
        "Código UG": "120625",
        "Nome UG": "GRUPAMENTO DE APOIO DO DISTRITO FED",
        "Código Modalidade Compra": "-99",
        "Modalidade Compra": "Pregão - Registro de Preço",
        "Número Processo": "67289000640202314",
        "Objeto": "Objeto: Pregão Eletrônico - Registro de preços para aquisição de material de equipamentos de cozinha para atender o GAP-DF.",
        "Situação Licitação": "Publicado",
        "Código Órgão Superior": "52000",
        "Nome Órgão Superior": "Ministério da Defesa",
        "Código Órgão": "52111",
        "Nome Órgão": "Comando da Aeronáutica",
        "UF": "DF",
        "Município": "BRASILIA",
        "Data Resultado Compra": "04/04/2024",
        "Data Abertura": "11/01/2024",
        "Valor Licitação": "7600,0000"
    },
    {
        "Número Licitação": "001272023",
        "Código UG": "120625",
        "Nome UG": "GRUPAMENTO DE APOIO DO DISTRITO FED",
        "Código Modalidade Compra": "-99",
        "Modalidade Compra": "Pregão - Registro de Preço",
        "Número Processo": "67289002316202322",
        "Objeto": "Objeto: Pregão Eletrônico - Aquisição de materiais para manutenção dos sistemas automotivos e similares nº 03 (três) da Seção de Transportes de Superfície  STS  do Grupamento de Apoio do Distrito Federal (GAP-DF) e das OM Apoiadas.",
        "Situação Licitação": "Publicado",
        "Código Órgão Superior": "52000",
        "Nome Órgão Superior": "Ministério da Defesa",
        "Código Órgão": "52111",
        "Nome Órgão": "Comando da Aeronáutica",
        "UF": "DF",
        "Município": "BRASILIA",
        "Data Resultado Compra": "02/04/2024",
        "Data Abertura": "26/12/2023",
        "Valor Licitação": "287,4000"
    },
    {
        "Número Licitação": "001282023",
        "Código UG": "120625",
        "Nome UG": "GRUPAMENTO DE APOIO DO DISTRITO FED",
        "Código Modalidade Compra": "-99",
        "Modalidade Compra": "Pregão - Registro de Preço",
        "Número Processo": "67289002316202322",
        "Objeto": "Objeto: Pregão Eletrônico - Aquisic a o de materiais para manutenc a o dos sistemas automotivos e similares n¿ 4(quatro) da STS",
        "Situação Licitação": "Publicado",
        "Código Órgão Superior": "52000",
        "Nome Órgão Superior": "Ministério da Defesa",
        "Código Órgão": "52111",
        "Nome Órgão": "Comando da Aeronáutica",
        "UF": "DF",
        "Município": "BRASILIA",
        "Data Resultado Compra": "04/04/2024",
        "Data Abertura": "27/12/2023",
        "Valor Licitação": "620,0000"
    },
    {
        "Número Licitação": "001762023",
        "Código UG": "250005",
        "Nome UG": "DEPARTAMENTO DE LOGISTICA EM SAUDE - DLOG",
        "Código Modalidade Compra": "-99",
        "Modalidade Compra": "Pregão - Registro de Preço",
        "Número Processo": "25000093567202347",
        "Objeto": "Objeto: Pregão Eletrônico - Registro de Preços para aquisição de Hemina Forma Farmacêutica: Concentrado P/ Solução Para Perfusão, Concentração: 25 MG/ML; Estiripentol Forma Farmacêutica: Pó Para Suspensão Oral, Concentração: 250 MG; Estiripentol Concentração: 250 MG; Estiripentol Concentração: 500 MG e Anacinra Forma Farmacêutica: Injetável, Adicional: Seringa Preenchida, Concentração: 150 MG/ML, conforme demais descrições contidas no Edital e seus Anexos.",
        "Situação Licitação": "Evento de Resultado de Julgame",
        "Código Órgão Superior": "36000",
        "Nome Órgão Superior": "Ministério da Saúde",
        "Código Órgão": "36000",
        "Nome Órgão": "Ministério da Saúde - Unidades com vínculo",
        "UF": "DF",
        "Município": "BRASILIA",
        "Data Resultado Compra": "01/04/2024",
        "Data Abertura": "09/01/2024",
        "Valor Licitação": "0,00"
    },
    {
        "Número Licitação": "900012024",
        "Código UG": "160072",
        "Nome UG": "11. DEPOSITO DE SUPRIMENTO",
        "Código Modalidade Compra": "-99",
        "Modalidade Compra": "Pregão - Registro de Preço",
        "Número Processo": "64456.007001/2023",
        "Objeto": "Objeto: Pregão Eletrônico - Aquisição de Materiais farmacológicos, Hospitalares e Odontológicos para o 11º Depósito de Suprimento.",
        "Situação Licitação": "Publicado",
        "Código Órgão Superior": "52000",
        "Nome Órgão Superior": "Ministério da Defesa",
        "Código Órgão": "52121",
        "Nome Órgão": "Comando do Exército",
        "UF": "DF",
        "Município": "BRASILIA",
        "Data Resultado Compra": "05/04/2024",
        "Data Abertura": "05/04/2024",
        "Valor Licitação": "0,00"
    },
    {
        "Número Licitação": "900012024",
        "Código UG": "168003",
        "Nome UG": "INDUSTRIA DE MATERIAL BELICO DO BRASIL - UA",
        "Código Modalidade Compra": "-99",
        "Modalidade Compra": "Pregão - Registro de Preço",
        "Número Processo": "386/2023",
        "Objeto": "Objeto: Pregão Eletrônico - Registro de preço para Aquisição de Materiais de Consumo, de itens de Gêneros de Alimentação, Homenagens, Expediente, Material de TIC, Acondicionamento e Embalagens, Copa e Cozinha, Limpeza e Produtos de Higienização, Manutenção de Bens Imóveis e Instalações, Manutenção de Bens Móveis, Elétrico e Eletrônico, Proteção e Segurança, Áudio Vídeo e Foto, Manutenção de Veículos, Bandeiras e Flâmulas, conforme Documento de Formalização da Demanda (DFD).",
        "Situação Licitação": "Evento de Resultado de Julgame",
        "Código Órgão Superior": "52000",
        "Nome Órgão Superior": "Ministério da Defesa",
        "Código Órgão": "52221",
        "Nome Órgão": "Indústria de Material Bélico do Brasil",
        "UF": "DF",
        "Município": "BRASILIA",
        "Data Resultado Compra": "04/04/2024",
        "Data Abertura": "25/01/2024",
        "Valor Licitação": "0,00"
    },
    {
        "Número Licitação": "900022024",
        "Código UG": "112408",
        "Nome UG": "HOSPITAL DAS FORCAS ARMADAS",
        "Código Modalidade Compra": "-99",
        "Modalidade Compra": "Pregão - Registro de Preço",
        "Número Processo": "60550025186202318",
        "Objeto": "Objeto: Pregão Eletrônico - Aquisição de Material para a Seção Central de Abastecimento de Material Médico-Hospitalar - SCAMMH. visa atender às necessidades do Hospital das Forças Armadas - HFA. Processo SUPER.GOV.BR (60550.025186/2023-18)",
        "Situação Licitação": "Evento de Resultado de Julgame",
        "Código Órgão Superior": "52000",
        "Nome Órgão Superior": "Ministério da Defesa",
        "Código Órgão": "52000",
        "Nome Órgão": "Ministério da Defesa - Unidades com vínculo",
        "UF": "DF",
        "Município": "BRASILIA",
        "Data Resultado Compra": "04/04/2024",
        "Data Abertura": "05/02/2024",
        "Valor Licitação": "0,00"
    },
    {
        "Número Licitação": "900022024",
        "Código UG": "170010",
        "Nome UG": "SECRET. ESPECIAL DA RECEITA FEDERAL DO BRASIL",
        "Código Modalidade Compra": "-99",
        "Modalidade Compra": "Pregão - Registro de Preço",
        "Número Processo": "18220101182202319",
        "Objeto": "Objeto: Pregão Eletrônico - Registro de Preços para Subscrição de licenças complementares à solução Microsoft MS-365 na modalidade de licenciamento Microsoft Enterprise Agreement Subscription (EAS), composto por 3 itens, incluindo serviços de suporte técnico, manutenção e atualização.",
        "Situação Licitação": "Publicado",
        "Código Órgão Superior": "25000",
        "Nome Órgão Superior": "Ministério da Fazenda",
        "Código Órgão": "25000",
        "Nome Órgão": "Ministério da Fazenda - Unidades com víncul",
        "UF": "DF",
        "Município": "BRASILIA",
        "Data Resultado Compra": "05/04/2024",
        "Data Abertura": "26/03/2024",
        "Valor Licitação": "0,00"
    },
    {
        "Número Licitação": "900032024",
        "Código UG": "110792",
        "Nome UG": "DIRETORIA DE LOGISTICA E GESTAO DOCUMENTAL",
        "Código Modalidade Compra": "-99",
        "Modalidade Compra": "Pregão - Registro de Preço",
        "Número Processo": "00404002160202345",
        "Objeto": "Objeto: Pregão Eletrônico - Serviços de assessoria técnica, organização e coordenação de eventos, realizados em terr. nacional, sob demanda, c/ fornecimento de insumos a fim de oferecer suporte às solenidades, congressos, conferências, seminários, palestras, exposições, wokshops, cursos e treinamentos em geral a serem realizados p/ AGU, nos diversos Estados da Federação, bem como p/ fornecimento de alimentação e bebidas p/ eventos institucionais, cfe condições, quant. e exigências do Termo de Referência.",
        "Situação Licitação": "Evento de Resultado de Julgame",
        "Código Órgão Superior": "63000",
        "Nome Órgão Superior": "Advocacia-Geral da União",
        "Código Órgão": "63000",
        "Nome Órgão": "Advocacia-Geral da União - Unidades com vín",
        "UF": "DF",
        "Município": "BRASILIA",
        "Data Resultado Compra": "02/04/2024",
        "Data Abertura": "15/03/2024",
        "Valor Licitação": "0,00"
    },
    {
        "Número Licitação": "900032024",
        "Código UG": "135100",
        "Nome UG": "COMPANHIA NACIONAL DE ABASTECIMENTO",
        "Código Modalidade Compra": "-99",
        "Modalidade Compra": "Pregão - Registro de Preço",
        "Número Processo": "21200007228202349",
        "Objeto": "Objeto: Pregão Eletrônico - A contratação em apreço tem por objetivo a aquisição de inseticidas líquido e sólido para o exercício 2024, sob o Sistema de Registro de Preços, visando tratamento fitossanitário de produtos agrícolas armazenados nas Unidades Armazenadoras (UAs) da Conab, conforme especificações, quantidades, exigências e condições, estabelecidas no Termo de Referência.",
        "Situação Licitação": "Evento de Resultado de Julgame",
        "Código Órgão Superior": "49000",
        "Nome Órgão Superior": "Ministério do Desenvolvimento Agrário e Agr",
        "Código Órgão": "22211",
        "Nome Órgão": "Companhia Nacional de Abastecimento",
        "UF": "DF",
        "Município": "BRASILIA",
        "Data Resultado Compra": "05/04/2024",
        "Data Abertura": "07/03/2024",
        "Valor Licitação": "0,00"
    },
    {
        "Número Licitação": "900032024",
        "Código UG": "168003",
        "Nome UG": "INDUSTRIA DE MATERIAL BELICO DO BRASIL - UA",
        "Código Modalidade Compra": "-99",
        "Modalidade Compra": "Pregão - Registro de Preço",
        "Número Processo": "00039/2024-IMBEL",
        "Objeto": "Objeto: Pregão Eletrônico - Aquisição de Material de Divulgação, Equipamento de Proteção Individual (EPI) e Materiais Diversos, do órgão Gerenciador, nos termos da tabela abaixo, conforme condições e exigências, estabelecidas no Termo de Referência.",
        "Situação Licitação": "Publicado",
        "Código Órgão Superior": "52000",
        "Nome Órgão Superior": "Ministério da Defesa",
        "Código Órgão": "52221",
        "Nome Órgão": "Indústria de Material Bélico do Brasil",
        "UF": "DF",
        "Município": "BRASILIA",
        "Data Resultado Compra": "04/04/2024",
        "Data Abertura": "05/02/2024",
        "Valor Licitação": "0,00"
    },
    {
        "Número Licitação": "900032024",
        "Código UG": "550005",
        "Nome UG": "COORDENACAO GERAL DE LICITACOES E CONTRATOS.",
        "Código Modalidade Compra": "-99",
        "Modalidade Compra": "Pregão - Registro de Preço",
        "Número Processo": "71000046924202303",
        "Objeto": "Objeto: Pregão Eletrônico - Registro de preço para contratação de serviços continuados de apoio administrativo de nível superior, a serem executados com regime de dedicação exclusiva de mão de obra, nos termos da tabela abaixo, conforme condições e exigências estabelecidas neste instrumento.",
        "Situação Licitação": "Publicado",
        "Código Órgão Superior": "55000",
        "Nome Órgão Superior": "Ministério do Desenvolvimento e Assistência",
        "Código Órgão": "55000",
        "Nome Órgão": "Ministério do Desenvolvimento e Assistência",
        "UF": "DF",
        "Município": "BRASILIA",
        "Data Resultado Compra": "03/04/2024",
        "Data Abertura": "29/02/2024",
        "Valor Licitação": "0,00"
    },
    {
        "Número Licitação": "900042024",
        "Código UG": "155007",
        "Nome UG": "EMPRESA BRASILEIRA DE SERVICOS HOSPITALARES",
        "Código Modalidade Compra": "-99",
        "Modalidade Compra": "Pregão - Registro de Preço",
        "Número Processo": "23477022824202334",
        "Objeto": "Objeto: Pregão Eletrônico - Aquisição de medicamentos antineoplásicos e citostáticos, pelo Sistema de Registro de Preços - SRP, para os Hospitais Universitários Federais (HUF) das regiões Norte, Nordeste, Centro-Oeste, Sudeste e Sul do Brasil, sob gestão da Empresa Brasileira de Serviços Hospitalares  Ebserh.",
        "Situação Licitação": "Evento de Adiamento Publicado",
        "Código Órgão Superior": "26000",
        "Nome Órgão Superior": "Ministério da Educação",
        "Código Órgão": "26443",
        "Nome Órgão": "Empresa Brasileira de Serviços Hospitalares",
        "UF": "DF",
        "Município": "BRASILIA",
        "Data Resultado Compra": "01/04/2024",
        "Data Abertura": "20/03/2024",
        "Valor Licitação": "0,00"
    },
    {
        "Número Licitação": "900052024",
        "Código UG": "110001",
        "Nome UG": "SECRETARIA DE ADMINISTRACAO/PR",
        "Código Modalidade Compra": "-99",
        "Modalidade Compra": "Pregão - Registro de Preço",
        "Número Processo": "00059000165202491",
        "Objeto": "Objeto: Pregão Eletrônico - Contratação de serviços de engenharia , constantes no Sistema Nacional de Pesquisa de Custos e Índices da Construção Civil SINAPI - DF , sob demanda , com fornecimento de materiais e mão de obra por meio do Sistema de Registros de Preços",
        "Situação Licitação": "Publicado",
        "Código Órgão Superior": "20000",
        "Nome Órgão Superior": "Presidência da República",
        "Código Órgão": "20101",
        "Nome Órgão": "Presidência da República",
        "UF": "DF",
        "Município": "BRASILIA",
        "Data Resultado Compra": "02/04/2024",
        "Data Abertura": "14/03/2024",
        "Valor Licitação": "0,00"
    },
    {
        "Número Licitação": "900052024",
        "Código UG": "155009",
        "Nome UG": "HOSPITAL UNIVERSITARIO DE BRASILIA",
        "Código Modalidade Compra": "-99",
        "Modalidade Compra": "Pregão - Registro de Preço",
        "Número Processo": "23522033052202373",
        "Objeto": "Objeto: Pregão Eletrônico - Aquisição de medicamentos Antineoplásicos, Oftalmologia, Grandes Volumes, Antimicrobianos e gerais para abastecimento da Unidade de Planejamento e Dimensionamento de Estoques, para atender às necessidades do Hospital Universitário de Brasília - HUB, referente ao Pregão 90.005/2024.",
        "Situação Licitação": "Publicado",
        "Código Órgão Superior": "26000",
        "Nome Órgão Superior": "Ministério da Educação",
        "Código Órgão": "26443",
        "Nome Órgão": "Empresa Brasileira de Serviços Hospitalares",
        "UF": "DF",
        "Município": "BRASILIA",
        "Data Resultado Compra": "05/04/2024",
        "Data Abertura": "05/04/2024",
        "Valor Licitação": "0,00"
    },
    {
        "Número Licitação": "900062024",
        "Código UG": "120006",
        "Nome UG": "GRUPAMENTO DE APOIO DE BRASILIA",
        "Código Modalidade Compra": "-99",
        "Modalidade Compra": "Pregão - Registro de Preço",
        "Número Processo": "67284005338202394",
        "Objeto": "Objeto: Pregão Eletrônico - Gêneros alimentícios Hortifruti",
        "Situação Licitação": "Publicado",
        "Código Órgão Superior": "52000",
        "Nome Órgão Superior": "Ministério da Defesa",
        "Código Órgão": "52111",
        "Nome Órgão": "Comando da Aeronáutica",
        "UF": "DF",
        "Município": "BRASILIA",
        "Data Resultado Compra": "02/04/2024",
        "Data Abertura": "14/03/2024",
        "Valor Licitação": "0,00"
    },
    {
        "Número Licitação": "900062024",
        "Código UG": "155009",
        "Nome UG": "HOSPITAL UNIVERSITARIO DE BRASILIA",
        "Código Modalidade Compra": "-99",
        "Modalidade Compra": "Pregão - Registro de Preço",
        "Número Processo": "23522029969202373",
        "Objeto": "Objeto: Pregão Eletrônico - Aquisição de Material Médico Hospitalar e insumos para Hemodiálise para a Unidade de Almoxarifado e Controle de Estoques, com Comodato de Equipamento, para o Hospital Universitário de Brasília - HUB, Referente ao Pregão 90.006/2024.",
        "Situação Licitação": "Publicado",
        "Código Órgão Superior": "26000",
        "Nome Órgão Superior": "Ministério da Educação",
        "Código Órgão": "26443",
        "Nome Órgão": "Empresa Brasileira de Serviços Hospitalares",
        "UF": "DF",
        "Município": "BRASILIA",
        "Data Resultado Compra": "03/04/2024",
        "Data Abertura": "03/04/2024",
        "Valor Licitação": "0,00"
    },
    {
        "Número Licitação": "900072024",
        "Código UG": "120006",
        "Nome UG": "GRUPAMENTO DE APOIO DE BRASILIA",
        "Código Modalidade Compra": "-99",
        "Modalidade Compra": "Pregão - Registro de Preço",
        "Número Processo": "67284005770202385",
        "Objeto": "Objeto: Pregão Eletrônico - Serviços de manutenção preventiva e corretiva nos aparelhos de Ar Condicionados split,",
        "Situação Licitação": "Publicado",
        "Código Órgão Superior": "52000",
        "Nome Órgão Superior": "Ministério da Defesa",
        "Código Órgão": "52111",
        "Nome Órgão": "Comando da Aeronáutica",
        "UF": "DF",
        "Município": "BRASILIA",
        "Data Resultado Compra": "02/04/2024",
        "Data Abertura": "15/03/2024",
        "Valor Licitação": "0,00"
    },
    {
        "Número Licitação": "900152024",
        "Código UG": "250005",
        "Nome UG": "DEPARTAMENTO DE LOGISTICA EM SAUDE - DLOG",
        "Código Modalidade Compra": "-99",
        "Modalidade Compra": "Pregão - Registro de Preço",
        "Número Processo": "25000020620202471",
        "Objeto": "Objeto: Pregão Eletrônico - Registro de Preços que visa à aquisição de Medicamentos para o combate à Dengue, para atender à solicitação do Departamento de Doenças Transmissíveis - DEDT, conforme as especificações constantes no Edital e seus Anexos.",
        "Situação Licitação": "Publicado",
        "Código Órgão Superior": "36000",
        "Nome Órgão Superior": "Ministério da Saúde",
        "Código Órgão": "36000",
        "Nome Órgão": "Ministério da Saúde - Unidades com vínculo",
        "UF": "DF",
        "Município": "BRASILIA",
        "Data Resultado Compra": "04/04/2024",
        "Data Abertura": "15/03/2024",
        "Valor Licitação": "0,00"
    }
]